<keymap version="1" name="IntelliJ IDEA Classic copy" parent="Mac OS X">
  <action id="Annotate">
    <keyboard-shortcut first-keystroke="meta semicolon" />
  </action>
  <action id="Back">
    <mouse-shortcut keystroke="button4" />
    <keyboard-shortcut first-keystroke="meta open_bracket" />
  </action>
  <action id="CompareTwoFiles" />
  <action id="Diff.ShowDiff" />
  <action id="EditorCodeBlockEnd" />
  <action id="EditorCodeBlockStart" />
  <action id="EditorDuplicate" />
  <action id="FileChooser.GotoDesktop" />
  <action id="FindUsages">
    <keyboard-shortcut first-keystroke="meta quote" />
  </action>
  <action id="Forward">
    <mouse-shortcut keystroke="button5" />
    <keyboard-shortcut first-keystroke="meta close_bracket" />
  </action>
  <action id="GotoImplementation">
    <keyboard-shortcut first-keystroke="meta d" />
  </action>
  <action id="GuiDesigner.Duplicate" />
  <action id="Images.Editor.ToggleGrid" />
  <action id="RunDashboard.CopyConfiguration" />
  <action id="SendEOF" />
  <action id="ShowProjectStructureSettings" />
  <action id="XDebugger.CopyWatch" />
</keymap>